{
  "UserAccount": [
    {
      "UserName": "sadasd",
      "Password": "asdsad",
      "Privilege": "Teacher",
      "Status": "Offline",
      "id": 1
    },
    {
      "UserName": "sadasd",
      "Password": "asdsad",
      "Privilege": "Teacher",
      "Status": "Offline",
      "id": 2
    },
    {
      "UserName": "sadasd",
      "Password": "asdsad",
      "Privilege": "Teacher",
      "Status": "Offline",
      "id": 3
    },
    {
      "UserName": "sadasd",
      "Password": "asdsad",
      "Privilege": "Teacher",
      "Status": "Offline",
      "id": 4
    },
    {
      "UserName": "asdasd",
      "Password": "asdasd",
      "Privilege": "Teacher",
      "Status": "Offline",
      "id": 5
    },
    {
      "UserName": "dsadas",
      "Password": "dasdasd",
      "Privilege": "Teacher",
      "Status": "Offline",
      "id": 6
    },
    {
      "UserName": "Kuyrai",
      "Password": "dddsdas",
      "Privilege": "Teacher",
      "Status": "Offline",
      "id": 7
    },
    {
      "UserName": "dsadas",
      "Password": "dasdsad",
      "Privilege": "Teacher",
      "Status": "Offline",
      "id": 8
    },
    {
      "UserName": "dsad",
      "Password": "dsad",
      "Privilege": "Student",
      "Status": "Online",
      "id": 9
    }
  ]
}